examplepackagefb1258/__init__.py
examplepackagefb1258/__main__.py
examplepackagefb1258/wisdom.py
powerdl-0.0.1.dist-info/LICENSE
powerdl-0.0.1.dist-info/METADATA
powerdl-0.0.1.dist-info/WHEEL
powerdl-0.0.1.dist-info/entry_points.txt
powerdl-0.0.1.dist-info/top_level.txt
powerdl-0.0.1.dist-info/RECORD
