Metadata-Version: 2.1
Name: powerdl
Version: 0.0.1
Summary: An example of a package developed with pyenv, built with build using setuptools, uploaded to PyPI using twine, and distributed via pip.
Author-email: Xianyan Jia <xianyan.xianyanjia@alibaba-inc.com>
License: GNU GENERAL PUBLIC LICENSE
Project-URL: Homepage, https://github.com/alibaba/chatlearn.git
Keywords: python,package,build,tutorial
Classifier: Programming Language :: Python :: 3
Classifier: Intended Audience :: Education
Classifier: License :: OSI Approved :: GNU General Public License v3 (GPLv3)
Classifier: Operating System :: OS Independent
Requires-Python: >=3.7
License-File: LICENSE
Provides-Extra: dev
Requires-Dist: pytest ; extra == 'dev'
